shuttl_time/__init__.py
shuttl_time/military_time.py
shuttl_time/military_time_window.py
shuttl_time/time.py
shuttl_time/time_window.py
shuttl_time/week_tIme_window.py
shuttl_time/week_time.py
shuttl_time/weekday.py
tests/__init__.py
tests/factories.py
tests/test_military_time_window.py
tests/test_time.py
tests/test_time_window.py
tests/test_week_time.py
tests/test_week_time_window.py
shuttl_time-0.0.5.dist-info/METADATA
shuttl_time-0.0.5.dist-info/WHEEL
shuttl_time-0.0.5.dist-info/top_level.txt
shuttl_time-0.0.5.dist-info/RECORD
