Metadata-Version: 2.1
Name: shuttl-time
Version: 0.0.5
Summary: Shuttl Time Library
Home-page: UNKNOWN
Author: himaniJoshi
Author-email: himani.joshi@shuttl.com
License: MIT
Platform: UNKNOWN
Classifier: Programming Language :: Python :: 3.7
Requires-Dist: pytz
Provides-Extra: dev
Requires-Dist: flake8 ; extra == 'dev'
Provides-Extra: test
Requires-Dist: pytest ; extra == 'test'
Requires-Dist: pytest-runner ; extra == 'test'
Requires-Dist: pytest-cov ; extra == 'test'
Requires-Dist: pytest-pep8 ; extra == 'test'
